views_evaluation/__init__.py
views_evaluation/evaluation/__init__.py
views_evaluation/evaluation/evaluation_manager.py
views_evaluation/evaluation/metric_calculators.py
views_evaluation/evaluation/metrics.py
views_evaluation-0.3.1.dist-info/METADATA
views_evaluation-0.3.1.dist-info/WHEEL
views_evaluation-0.3.1.dist-info/RECORD
