Metadata-Version: 2.3
Name: views_evaluation
Version: 0.3.1
Summary: 
Author: Xiaolong Sun
Author-email: xiaolong.sun@pcr.uu.se
Requires-Python: >=3.11,<3.15
Classifier: Programming Language :: Python :: 3
Classifier: Programming Language :: Python :: 3.11
Classifier: Programming Language :: Python :: 3.12
Classifier: Programming Language :: Python :: 3.13
Requires-Dist: numpy (>=1.26.4,<2.0.0)
Requires-Dist: pandas (>=1.5.3,<2.0.0)
Requires-Dist: properscoring (>=0.1.0,<0.2.0)
Requires-Dist: pytest (>=8.3.3,<9.0.0)
Requires-Dist: scikit-learn (>=1.6.0,<2.0.0)
